<DOMSymbolItem xmlns:xsi="http://www.w3.org/2001/XMLSchema-instance" xmlns="http://ns.adobe.com/xfl/2008/" name="casa7" itemID="67460682-000003f8" lastModified="1732644670">
  <timeline>
    <DOMTimeline name="casa7" layerDepthEnabled="true">
      <layers>
        <DOMLayer name="Layer_1" color="#00FFFF" current="true" isSelected="true">
          <frames>
            <DOMFrame index="0" keyMode="9728">
              <elements>
                <DOMBitmapInstance libraryItemName="Bitmap 5.png">
                  <matrix>
                    <Matrix a="1.49998474121094" d="1.49998474121094" tx="-105" ty="-221"/>
                  </matrix>
                  <transformationPoint>
                    <Point x="69.65" y="96.35"/>
                  </transformationPoint>
                </DOMBitmapInstance>
              </elements>
            </DOMFrame>
          </frames>
        </DOMLayer>
      </layers>
    </DOMTimeline>
  </timeline>
</DOMSymbolItem>