{
  "frames": {
    "boca/birra/10": {
      "frame": {
        "x": 0,
        "y": 0,
        "w": 10,
        "h": 19
      },
      "rotated": false,
      "trimmed": true,
      "spriteSourceSize": {
        "x": 2,
        "y": 2,
        "w": 10,
        "h": 19
      },
      "sourceSize": {
        "w": 12,
        "h": 21
      },
      "pivot": {
        "x": 0.5,
        "y": 0.5
      }
    },
    "boca/birra/11": {
      "frame": {
        "x": 0,
        "y": 19,
        "w": 10,
        "h": 19
      },
      "rotated": false,
      "trimmed": true,
      "spriteSourceSize": {
        "x": 2,
        "y": 2,
        "w": 10,
        "h": 19
      },
      "sourceSize": {
        "w": 12,
        "h": 21
      },
      "pivot": {
        "x": 0.5,
        "y": 0.5
      }
    },
    "boca/caminar/1": {
      "frame": {
        "x": 0,
        "y": 38,
        "w": 8,
        "h": 19
      },
      "rotated": false,
      "trimmed": true,
      "spriteSourceSize": {
        "x": 1,
        "y": 1,
        "w": 8,
        "h": 19
      },
      "sourceSize": {
        "w": 12,
        "h": 21
      },
      "pivot": {
        "x": 0.5,
        "y": 0.5
      }
    },
    "boca/caminar/5": {
      "frame": {
        "x": 0,
        "y": 57,
        "w": 8,
        "h": 19
      },
      "rotated": false,
      "trimmed": true,
      "spriteSourceSize": {
        "x": 1,
        "y": 1,
        "w": 8,
        "h": 19
      },
      "sourceSize": {
        "w": 12,
        "h": 21
      },
      "pivot": {
        "x": 0.5,
        "y": 0.5
      }
    },
    "boca/tirapiedra/1": {
      "frame": {
        "x": 0,
        "y": 76,
        "w": 7,
        "h": 19
      },
      "rotated": false,
      "trimmed": true,
      "spriteSourceSize": {
        "x": 2,
        "y": 1,
        "w": 7,
        "h": 19
      },
      "sourceSize": {
        "w": 12,
        "h": 21
      },
      "pivot": {
        "x": 0.5,
        "y": 0.5
      }
    },
    "boca/caminar/2": {
      "frame": {
        "x": 0,
        "y": 95,
        "w": 6,
        "h": 19
      },
      "rotated": false,
      "trimmed": true,
      "spriteSourceSize": {
        "x": 2,
        "y": 1,
        "w": 6,
        "h": 19
      },
      "sourceSize": {
        "w": 12,
        "h": 21
      },
      "pivot": {
        "x": 0.5,
        "y": 0.5
      }
    },
    "boca/caminar/4": {
      "frame": {
        "x": 0,
        "y": 114,
        "w": 6,
        "h": 19
      },
      "rotated": false,
      "trimmed": true,
      "spriteSourceSize": {
        "x": 2,
        "y": 1,
        "w": 6,
        "h": 19
      },
      "sourceSize": {
        "w": 12,
        "h": 21
      },
      "pivot": {
        "x": 0.5,
        "y": 0.5
      }
    },
    "boca/tirapiedra/2": {
      "frame": {
        "x": 0,
        "y": 133,
        "w": 11,
        "h": 18
      },
      "rotated": false,
      "trimmed": true,
      "spriteSourceSize": {
        "x": 1,
        "y": 2,
        "w": 11,
        "h": 18
      },
      "sourceSize": {
        "w": 12,
        "h": 21
      },
      "pivot": {
        "x": 0.5,
        "y": 0.5
      }
    },
    "boca/atacar/3": {
      "frame": {
        "x": 6,
        "y": 95,
        "w": 10,
        "h": 18
      },
      "rotated": false,
      "trimmed": true,
      "spriteSourceSize": {
        "x": 2,
        "y": 2,
        "w": 10,
        "h": 18
      },
      "sourceSize": {
        "w": 12,
        "h": 21
      },
      "pivot": {
        "x": 0.5,
        "y": 0.5
      }
    },
    "boca/birra/01": {
      "frame": {
        "x": 7,
        "y": 76,
        "w": 10,
        "h": 18
      },
      "rotated": false,
      "trimmed": true,
      "spriteSourceSize": {
        "x": 2,
        "y": 2,
        "w": 10,
        "h": 18
      },
      "sourceSize": {
        "w": 12,
        "h": 21
      },
      "pivot": {
        "x": 0.5,
        "y": 0.5
      }
    },
    "boca/birra/03": {
      "frame": {
        "x": 6,
        "y": 113,
        "w": 10,
        "h": 18
      },
      "rotated": false,
      "trimmed": true,
      "spriteSourceSize": {
        "x": 2,
        "y": 2,
        "w": 10,
        "h": 18
      },
      "sourceSize": {
        "w": 12,
        "h": 21
      },
      "pivot": {
        "x": 0.5,
        "y": 0.5
      }
    },
    "boca/birra/05": {
      "frame": {
        "x": 8,
        "y": 38,
        "w": 10,
        "h": 18
      },
      "rotated": false,
      "trimmed": true,
      "spriteSourceSize": {
        "x": 2,
        "y": 2,
        "w": 10,
        "h": 18
      },
      "sourceSize": {
        "w": 12,
        "h": 21
      },
      "pivot": {
        "x": 0.5,
        "y": 0.5
      }
    },
    "boca/birra/07": {
      "frame": {
        "x": 8,
        "y": 56,
        "w": 10,
        "h": 18
      },
      "rotated": false,
      "trimmed": true,
      "spriteSourceSize": {
        "x": 2,
        "y": 2,
        "w": 10,
        "h": 18
      },
      "sourceSize": {
        "w": 12,
        "h": 21
      },
      "pivot": {
        "x": 0.5,
        "y": 0.5
      }
    },
    "boca/birra/08": {
      "frame": {
        "x": 10,
        "y": 0,
        "w": 10,
        "h": 18
      },
      "rotated": false,
      "trimmed": true,
      "spriteSourceSize": {
        "x": 2,
        "y": 2,
        "w": 10,
        "h": 18
      },
      "sourceSize": {
        "w": 12,
        "h": 21
      },
      "pivot": {
        "x": 0.5,
        "y": 0.5
      }
    },
    "boca/birra/09": {
      "frame": {
        "x": 10,
        "y": 18,
        "w": 10,
        "h": 18
      },
      "rotated": false,
      "trimmed": true,
      "spriteSourceSize": {
        "x": 2,
        "y": 2,
        "w": 10,
        "h": 18
      },
      "sourceSize": {
        "w": 12,
        "h": 21
      },
      "pivot": {
        "x": 0.5,
        "y": 0.5
      }
    },
    "boca/meo/10": {
      "frame": {
        "x": 0,
        "y": 151,
        "w": 10,
        "h": 18
      },
      "rotated": false,
      "trimmed": true,
      "spriteSourceSize": {
        "x": 2,
        "y": 3,
        "w": 10,
        "h": 18
      },
      "sourceSize": {
        "w": 12,
        "h": 21
      },
      "pivot": {
        "x": 0.5,
        "y": 0.5
      }
    },
    "boca/meo/11": {
      "frame": {
        "x": 0,
        "y": 169,
        "w": 10,
        "h": 18
      },
      "rotated": false,
      "trimmed": true,
      "spriteSourceSize": {
        "x": 2,
        "y": 3,
        "w": 10,
        "h": 18
      },
      "sourceSize": {
        "w": 12,
        "h": 21
      },
      "pivot": {
        "x": 0.5,
        "y": 0.5
      }
    },
    "boca/meo/12": {
      "frame": {
        "x": 0,
        "y": 187,
        "w": 10,
        "h": 18
      },
      "rotated": false,
      "trimmed": true,
      "spriteSourceSize": {
        "x": 2,
        "y": 3,
        "w": 10,
        "h": 18
      },
      "sourceSize": {
        "w": 12,
        "h": 21
      },
      "pivot": {
        "x": 0.5,
        "y": 0.5
      }
    },
    "boca/tirapiedra/3": {
      "frame": {
        "x": 0,
        "y": 205,
        "w": 10,
        "h": 18
      },
      "rotated": false,
      "trimmed": true,
      "spriteSourceSize": {
        "x": 2,
        "y": 2,
        "w": 10,
        "h": 18
      },
      "sourceSize": {
        "w": 12,
        "h": 21
      },
      "pivot": {
        "x": 0.5,
        "y": 0.5
      }
    },
    "boca/atacar/1": {
      "frame": {
        "x": 0,
        "y": 223,
        "w": 9,
        "h": 18
      },
      "rotated": false,
      "trimmed": true,
      "spriteSourceSize": {
        "x": 1,
        "y": 2,
        "w": 9,
        "h": 18
      },
      "sourceSize": {
        "w": 12,
        "h": 21
      },
      "pivot": {
        "x": 0.5,
        "y": 0.5
      }
    },
    "boca/atacar/2": {
      "frame": {
        "x": 0,
        "y": 241,
        "w": 9,
        "h": 18
      },
      "rotated": false,
      "trimmed": true,
      "spriteSourceSize": {
        "x": 1,
        "y": 2,
        "w": 9,
        "h": 18
      },
      "sourceSize": {
        "w": 12,
        "h": 21
      },
      "pivot": {
        "x": 0.5,
        "y": 0.5
      }
    },
    "boca/atacar/4": {
      "frame": {
        "x": 0,
        "y": 259,
        "w": 9,
        "h": 18
      },
      "rotated": false,
      "trimmed": true,
      "spriteSourceSize": {
        "x": 2,
        "y": 2,
        "w": 9,
        "h": 18
      },
      "sourceSize": {
        "w": 12,
        "h": 21
      },
      "pivot": {
        "x": 0.5,
        "y": 0.5
      }
    },
    "boca/birra/00": {
      "frame": {
        "x": 0,
        "y": 277,
        "w": 9,
        "h": 18
      },
      "rotated": false,
      "trimmed": true,
      "spriteSourceSize": {
        "x": 2,
        "y": 2,
        "w": 9,
        "h": 18
      },
      "sourceSize": {
        "w": 12,
        "h": 21
      },
      "pivot": {
        "x": 0.5,
        "y": 0.5
      }
    },
    "boca/birra/02": {
      "frame": {
        "x": 0,
        "y": 295,
        "w": 9,
        "h": 18
      },
      "rotated": false,
      "trimmed": true,
      "spriteSourceSize": {
        "x": 2,
        "y": 2,
        "w": 9,
        "h": 18
      },
      "sourceSize": {
        "w": 12,
        "h": 21
      },
      "pivot": {
        "x": 0.5,
        "y": 0.5
      }
    },
    "boca/caminar/0": {
      "frame": {
        "x": 0,
        "y": 313,
        "w": 9,
        "h": 18
      },
      "rotated": false,
      "trimmed": true,
      "spriteSourceSize": {
        "x": 1,
        "y": 2,
        "w": 9,
        "h": 18
      },
      "sourceSize": {
        "w": 12,
        "h": 21
      },
      "pivot": {
        "x": 0.5,
        "y": 0.5
      }
    },
    "boca/meo/08": {
      "frame": {
        "x": 0,
        "y": 331,
        "w": 9,
        "h": 18
      },
      "rotated": false,
      "trimmed": true,
      "spriteSourceSize": {
        "x": 2,
        "y": 3,
        "w": 9,
        "h": 18
      },
      "sourceSize": {
        "w": 12,
        "h": 21
      },
      "pivot": {
        "x": 0.5,
        "y": 0.5
      }
    },
    "boca/meo/09": {
      "frame": {
        "x": 0,
        "y": 349,
        "w": 9,
        "h": 18
      },
      "rotated": false,
      "trimmed": true,
      "spriteSourceSize": {
        "x": 2,
        "y": 3,
        "w": 9,
        "h": 18
      },
      "sourceSize": {
        "w": 12,
        "h": 21
      },
      "pivot": {
        "x": 0.5,
        "y": 0.5
      }
    },
    "boca/atacar/0": {
      "frame": {
        "x": 0,
        "y": 367,
        "w": 8,
        "h": 18
      },
      "rotated": false,
      "trimmed": true,
      "spriteSourceSize": {
        "x": 2,
        "y": 2,
        "w": 8,
        "h": 18
      },
      "sourceSize": {
        "w": 12,
        "h": 21
      },
      "pivot": {
        "x": 0.5,
        "y": 0.5
      }
    },
    "boca/atacar/5": {
      "frame": {
        "x": 0,
        "y": 385,
        "w": 8,
        "h": 18
      },
      "rotated": false,
      "trimmed": true,
      "spriteSourceSize": {
        "x": 2,
        "y": 2,
        "w": 8,
        "h": 18
      },
      "sourceSize": {
        "w": 12,
        "h": 21
      },
      "pivot": {
        "x": 0.5,
        "y": 0.5
      }
    },
    "boca/meo/07": {
      "frame": {
        "x": 0,
        "y": 403,
        "w": 8,
        "h": 18
      },
      "rotated": false,
      "trimmed": true,
      "spriteSourceSize": {
        "x": 2,
        "y": 3,
        "w": 8,
        "h": 18
      },
      "sourceSize": {
        "w": 12,
        "h": 21
      },
      "pivot": {
        "x": 0.5,
        "y": 0.5
      }
    },
    "boca/muerte/0": {
      "frame": {
        "x": 0,
        "y": 421,
        "w": 8,
        "h": 18
      },
      "rotated": false,
      "trimmed": true,
      "spriteSourceSize": {
        "x": 2,
        "y": 2,
        "w": 8,
        "h": 18
      },
      "sourceSize": {
        "w": 12,
        "h": 21
      },
      "pivot": {
        "x": 0.5,
        "y": 0.5
      }
    },
    "boca/atacar/6": {
      "frame": {
        "x": 0,
        "y": 439,
        "w": 7,
        "h": 18
      },
      "rotated": false,
      "trimmed": true,
      "spriteSourceSize": {
        "x": 2,
        "y": 2,
        "w": 7,
        "h": 18
      },
      "sourceSize": {
        "w": 12,
        "h": 21
      },
      "pivot": {
        "x": 0.5,
        "y": 0.5
      }
    },
    "boca/meo/00": {
      "frame": {
        "x": 0,
        "y": 457,
        "w": 7,
        "h": 18
      },
      "rotated": false,
      "trimmed": true,
      "spriteSourceSize": {
        "x": 2,
        "y": 2,
        "w": 7,
        "h": 18
      },
      "sourceSize": {
        "w": 12,
        "h": 21
      },
      "pivot": {
        "x": 0.5,
        "y": 0.5
      }
    },
    "boca/meo/01": {
      "frame": {
        "x": 0,
        "y": 475,
        "w": 7,
        "h": 18
      },
      "rotated": false,
      "trimmed": true,
      "spriteSourceSize": {
        "x": 2,
        "y": 3,
        "w": 7,
        "h": 18
      },
      "sourceSize": {
        "w": 12,
        "h": 21
      },
      "pivot": {
        "x": 0.5,
        "y": 0.5
      }
    },
    "boca/meo/02": {
      "frame": {
        "x": 0,
        "y": 493,
        "w": 7,
        "h": 18
      },
      "rotated": false,
      "trimmed": true,
      "spriteSourceSize": {
        "x": 2,
        "y": 3,
        "w": 7,
        "h": 18
      },
      "sourceSize": {
        "w": 12,
        "h": 21
      },
      "pivot": {
        "x": 0.5,
        "y": 0.5
      }
    },
    "boca/meo/04": {
      "frame": {
        "x": 0,
        "y": 511,
        "w": 7,
        "h": 18
      },
      "rotated": false,
      "trimmed": true,
      "spriteSourceSize": {
        "x": 2,
        "y": 3,
        "w": 7,
        "h": 18
      },
      "sourceSize": {
        "w": 12,
        "h": 21
      },
      "pivot": {
        "x": 0.5,
        "y": 0.5
      }
    },
    "boca/meo/05": {
      "frame": {
        "x": 0,
        "y": 529,
        "w": 7,
        "h": 18
      },
      "rotated": false,
      "trimmed": true,
      "spriteSourceSize": {
        "x": 2,
        "y": 3,
        "w": 7,
        "h": 18
      },
      "sourceSize": {
        "w": 12,
        "h": 21
      },
      "pivot": {
        "x": 0.5,
        "y": 0.5
      }
    },
    "boca/meo/06": {
      "frame": {
        "x": 0,
        "y": 547,
        "w": 7,
        "h": 18
      },
      "rotated": false,
      "trimmed": true,
      "spriteSourceSize": {
        "x": 2,
        "y": 3,
        "w": 7,
        "h": 18
      },
      "sourceSize": {
        "w": 12,
        "h": 21
      },
      "pivot": {
        "x": 0.5,
        "y": 0.5
      }
    },
    "boca/tirapiedra/4": {
      "frame": {
        "x": 0,
        "y": 565,
        "w": 7,
        "h": 18
      },
      "rotated": false,
      "trimmed": true,
      "spriteSourceSize": {
        "x": 3,
        "y": 2,
        "w": 7,
        "h": 18
      },
      "sourceSize": {
        "w": 12,
        "h": 21
      },
      "pivot": {
        "x": 0.5,
        "y": 0.5
      }
    },
    "boca/caminar/3": {
      "frame": {
        "x": 0,
        "y": 583,
        "w": 6,
        "h": 18
      },
      "rotated": false,
      "trimmed": true,
      "spriteSourceSize": {
        "x": 2,
        "y": 2,
        "w": 6,
        "h": 18
      },
      "sourceSize": {
        "w": 12,
        "h": 21
      },
      "pivot": {
        "x": 0.5,
        "y": 0.5
      }
    },
    "boca/idle": {
      "frame": {
        "x": 0,
        "y": 601,
        "w": 6,
        "h": 18
      },
      "rotated": false,
      "trimmed": true,
      "spriteSourceSize": {
        "x": 2,
        "y": 2,
        "w": 6,
        "h": 18
      },
      "sourceSize": {
        "w": 12,
        "h": 21
      },
      "pivot": {
        "x": 0.5,
        "y": 0.5
      }
    },
    "boca/meo/13": {
      "frame": {
        "x": 0,
        "y": 619,
        "w": 6,
        "h": 18
      },
      "rotated": false,
      "trimmed": true,
      "spriteSourceSize": {
        "x": 2,
        "y": 3,
        "w": 6,
        "h": 18
      },
      "sourceSize": {
        "w": 12,
        "h": 21
      },
      "pivot": {
        "x": 0.5,
        "y": 0.5
      }
    },
    "boca/tirapiedra/0": {
      "frame": {
        "x": 0,
        "y": 637,
        "w": 6,
        "h": 18
      },
      "rotated": false,
      "trimmed": true,
      "spriteSourceSize": {
        "x": 1,
        "y": 2,
        "w": 6,
        "h": 18
      },
      "sourceSize": {
        "w": 12,
        "h": 21
      },
      "pivot": {
        "x": 0.5,
        "y": 0.5
      }
    },
    "boca/tirapiedra/5": {
      "frame": {
        "x": 0,
        "y": 655,
        "w": 6,
        "h": 18
      },
      "rotated": false,
      "trimmed": true,
      "spriteSourceSize": {
        "x": 2,
        "y": 2,
        "w": 6,
        "h": 18
      },
      "sourceSize": {
        "w": 12,
        "h": 21
      },
      "pivot": {
        "x": 0.5,
        "y": 0.5
      }
    },
    "boca/muerte/1": {
      "frame": {
        "x": 0,
        "y": 673,
        "w": 8,
        "h": 17
      },
      "rotated": false,
      "trimmed": true,
      "spriteSourceSize": {
        "x": 2,
        "y": 3,
        "w": 8,
        "h": 17
      },
      "sourceSize": {
        "w": 12,
        "h": 21
      },
      "pivot": {
        "x": 0.5,
        "y": 0.5
      }
    },
    "boca/salto/0": {
      "frame": {
        "x": 6,
        "y": 583,
        "w": 8,
        "h": 17
      },
      "rotated": false,
      "trimmed": true,
      "spriteSourceSize": {
        "x": 1,
        "y": 3,
        "w": 8,
        "h": 17
      },
      "sourceSize": {
        "w": 12,
        "h": 21
      },
      "pivot": {
        "x": 0.5,
        "y": 0.5
      }
    },
    "boca/salto/2": {
      "frame": {
        "x": 6,
        "y": 600,
        "w": 8,
        "h": 17
      },
      "rotated": false,
      "trimmed": true,
      "spriteSourceSize": {
        "x": 3,
        "y": 1,
        "w": 8,
        "h": 17
      },
      "sourceSize": {
        "w": 12,
        "h": 21
      },
      "pivot": {
        "x": 0.5,
        "y": 0.5
      }
    },
    "boca/salto/3": {
      "frame": {
        "x": 6,
        "y": 617,
        "w": 8,
        "h": 17
      },
      "rotated": false,
      "trimmed": true,
      "spriteSourceSize": {
        "x": 2,
        "y": 0,
        "w": 8,
        "h": 17
      },
      "sourceSize": {
        "w": 12,
        "h": 21
      },
      "pivot": {
        "x": 0.5,
        "y": 0.5
      }
    },
    "boca/salto/5": {
      "frame": {
        "x": 6,
        "y": 634,
        "w": 8,
        "h": 17
      },
      "rotated": false,
      "trimmed": true,
      "spriteSourceSize": {
        "x": 2,
        "y": 2,
        "w": 8,
        "h": 17
      },
      "sourceSize": {
        "w": 12,
        "h": 21
      },
      "pivot": {
        "x": 0.5,
        "y": 0.5
      }
    },
    "boca/salto/6": {
      "frame": {
        "x": 6,
        "y": 651,
        "w": 8,
        "h": 17
      },
      "rotated": false,
      "trimmed": true,
      "spriteSourceSize": {
        "x": 2,
        "y": 3,
        "w": 8,
        "h": 17
      },
      "sourceSize": {
        "w": 12,
        "h": 21
      },
      "pivot": {
        "x": 0.5,
        "y": 0.5
      }
    },
    "boca/muerte/2": {
      "frame": {
        "x": 7,
        "y": 439,
        "w": 9,
        "h": 14
      },
      "rotated": false,
      "trimmed": true,
      "spriteSourceSize": {
        "x": 2,
        "y": 6,
        "w": 9,
        "h": 14
      },
      "sourceSize": {
        "w": 12,
        "h": 21
      },
      "pivot": {
        "x": 0.5,
        "y": 0.5
      }
    },
    "boca/muerte/3": {
      "frame": {
        "x": 8,
        "y": 367,
        "w": 9,
        "h": 12
      },
      "rotated": false,
      "trimmed": true,
      "spriteSourceSize": {
        "x": 2,
        "y": 9,
        "w": 9,
        "h": 12
      },
      "sourceSize": {
        "w": 12,
        "h": 21
      },
      "pivot": {
        "x": 0.5,
        "y": 0.5
      }
    },
    "boca/muerte/5": {
      "frame": {
        "x": 8,
        "y": 379,
        "w": 12,
        "h": 8
      },
      "rotated": true,
      "trimmed": true,
      "spriteSourceSize": {
        "x": 0,
        "y": 13,
        "w": 12,
        "h": 8
      },
      "sourceSize": {
        "w": 12,
        "h": 21
      },
      "pivot": {
        "x": 0.5,
        "y": 0.5
      }
    },
    "boca/muerte/6": {
      "frame": {
        "x": 8,
        "y": 391,
        "w": 12,
        "h": 8
      },
      "rotated": true,
      "trimmed": true,
      "spriteSourceSize": {
        "x": 0,
        "y": 13,
        "w": 12,
        "h": 8
      },
      "sourceSize": {
        "w": 12,
        "h": 21
      },
      "pivot": {
        "x": 0.5,
        "y": 0.5
      }
    },
    "boca/muerte/4": {
      "frame": {
        "x": 8,
        "y": 403,
        "w": 11,
        "h": 11
      },
      "rotated": false,
      "trimmed": true,
      "spriteSourceSize": {
        "x": 1,
        "y": 10,
        "w": 11,
        "h": 11
      },
      "sourceSize": {
        "w": 12,
        "h": 21
      },
      "pivot": {
        "x": 0.5,
        "y": 0.5
      }
    },
    "boca/birra/06": {
      "frame": {
        "x": 7,
        "y": 76,
        "w": 10,
        "h": 18
      },
      "rotated": false,
      "trimmed": true,
      "spriteSourceSize": {
        "x": 2,
        "y": 2,
        "w": 10,
        "h": 18
      },
      "sourceSize": {
        "w": 12,
        "h": 21
      },
      "pivot": {
        "x": 0.5,
        "y": 0.5
      }
    },
    "boca/birra/04": {
      "frame": {
        "x": 0,
        "y": 295,
        "w": 9,
        "h": 18
      },
      "rotated": false,
      "trimmed": true,
      "spriteSourceSize": {
        "x": 2,
        "y": 2,
        "w": 9,
        "h": 18
      },
      "sourceSize": {
        "w": 12,
        "h": 21
      },
      "pivot": {
        "x": 0.5,
        "y": 0.5
      }
    },
    "boca/meo/03": {
      "frame": {
        "x": 0,
        "y": 493,
        "w": 7,
        "h": 18
      },
      "rotated": false,
      "trimmed": true,
      "spriteSourceSize": {
        "x": 2,
        "y": 3,
        "w": 7,
        "h": 18
      },
      "sourceSize": {
        "w": 12,
        "h": 21
      },
      "pivot": {
        "x": 0.5,
        "y": 0.5
      }
    }
  },
  "animations": {
    "birra": [
      "boca/birra/00",
      "boca/birra/01",
      "boca/birra/02",
      "boca/birra/03",
      "boca/birra/04",
      "boca/birra/05",
      "boca/birra/06",
      "boca/birra/07",
      "boca/birra/08",
      "boca/birra/09",
      "boca/birra/10",
      "boca/birra/11"
    ],
    "tirapiedra": [
      "boca/tirapiedra/0",
      "boca/tirapiedra/1",
      "boca/tirapiedra/2",
      "boca/tirapiedra/3",
      "boca/tirapiedra/4",
      "boca/tirapiedra/5"
    ],
    "golpe": [
      "boca/atacar/0",
      "boca/atacar/1",
      "boca/atacar/2",
      "boca/atacar/3",
      "boca/atacar/4",
      "boca/atacar/5",
      "boca/atacar/6"
    ],
    "meo": [
      "boca/meo/00",
      "boca/meo/01",
      "boca/meo/02",
      "boca/meo/03",
      "boca/meo/04",
      "boca/meo/05",
      "boca/meo/06",
      "boca/meo/07",
      "boca/meo/08",
      "boca/meo/09",
      "boca/meo/10",
      "boca/meo/11",
      "boca/meo/12",
      "boca/meo/13"
    ],
    "muerte": [
      "boca/muerte/0",
      "boca/muerte/1",
      "boca/muerte/2",
      "boca/muerte/3",
      "boca/muerte/4",
      "boca/muerte/5",
      "boca/muerte/6"
    ],
    "parado": [
      "boca/idle"
    ],
    "salto": [
      "boca/salto/0",
      "boca/salto/2",
      "boca/salto/3",
      "boca/salto/5",
      "boca/salto/6"
    ],
    "camina": [
      "boca/caminar/0",
      "boca/caminar/1",
      "boca/caminar/2",
      "boca/caminar/3",
      "boca/caminar/4",
      "boca/caminar/5"
    ],
    "corre": [
      "boca/caminar/0",
      "boca/caminar/2",
      "boca/caminar/4"
    ],
    "recibir_golpe": [
      "boca/muerte/0",
      "boca/muerte1",
      "boca/idle"
    ]
  },
  "meta": {
    "app": "http://free-tex-packer.com",
    "version": "0.6.7",
    "image": "boca.png",
    "format": "RGBA8888",
    "size": {
      "w": 20,
      "h": 690
    },
    "scale": 1
  }
}